multisafepay_payment/__init__.py
multisafepay_payment/forms.py
multisafepay_payment/urls.py
multisafepay_payment/views.py
multisafepay_payment/commerce/__init__.py
multisafepay_payment/commerce/checkout.py
multisafepay_payment/commerce/dummy.py
multisafepay_payment/extensions/__init__.py
multisafepay_payment/extensions/multisafepay.py
multisafepay_payment/templates/multisafepay_payment.html
multisafepay_payment/tests/__init__.py
multisafepay_payment/tests/mixins.py
multisafepay_payment/tests/test_service.py
multisafepay_payment/tests/test_views.py
multisafepay_payment-2.0.0.dist-info/METADATA
multisafepay_payment-2.0.0.dist-info/WHEEL
multisafepay_payment-2.0.0.dist-info/top_level.txt
multisafepay_payment-2.0.0.dist-info/RECORD
